asset_inventory/__init__.py
asset_inventory/__main__.py
asset_inventory/asset_inventory.py
asset_inventory/models/__init__.py
asset_inventory/models/device.py
asset_inventory/models/inventory.py
asset_inventory/models/server.py
asset_inventory-0.0.7.dist-info/LICENSE
asset_inventory-0.0.7.dist-info/METADATA
asset_inventory-0.0.7.dist-info/WHEEL
asset_inventory-0.0.7.dist-info/top_level.txt
asset_inventory-0.0.7.dist-info/RECORD
